elexsolver/LinearSolver.py
elexsolver/OLSRegressionSolver.py
elexsolver/QuantileRegressionSolver.py
elexsolver/TransitionMatrixSolver.py
elexsolver/TransitionSolver.py
elexsolver/__init__.py
elexsolver/logging.py
elex_solver-2.1.1.dist-info/METADATA
elex_solver-2.1.1.dist-info/WHEEL
elex_solver-2.1.1.dist-info/top_level.txt
elex_solver-2.1.1.dist-info/RECORD
