Metadata-Version: 2.1
Name: elex-solver
Version: 2.1.1
Summary: A package for optimization solvers
License: MIT
Classifier: Intended Audience :: Developers
Classifier: License :: OSI Approved :: MIT License
Classifier: Programming Language :: Python
Classifier: Programming Language :: Python :: 3.11
Requires-Dist: cvxpy~=1.5
Requires-Dist: numpy~=2.1
Requires-Dist: scipy~=1.14
